setup.py
tss.py
tss.egg-info/PKG-INFO
tss.egg-info/SOURCES.txt
tss.egg-info/dependency_links.txt
tss.egg-info/top_level.txt